Metadata-Version: 2.3
Name: yasol
Version: 0.2.0
Summary: Python SDK for SOL
Project-URL: homepage, https://github.com/mohanson/pysol
Author-email: Mohanson <mohanson@outlook.com>
License: MIT License
Requires-Dist: requests
